<annotation>
    <folder>Images</folder>
    <filename>hard_hat_workers2496.png</filename>
    <path>C:\my-files\New folder\woboAI\Section 3\Images\hard_hat_workers2496.png</path>
    <source>
        <database>Unknown</database>
    </source>
    <size>
        <width>416</width>
        <height>416</height>
        <depth>3</depth>
    </size>
    <segmented>0</segmented>
    <object>
        <name>helmet</name>
        <pose>Unspecified</pose>
        <truncated>0</truncated>
        <difficult>0</difficult>
        <bndbox>
            <xmin>97</xmin>
            <ymin>93</ymin>
            <xmax>138</xmax>
            <ymax>142</ymax>
        </bndbox>
    </object>    <object>
        <name>helmet</name>
        <pose>Unspecified</pose>
        <truncated>0</truncated>
        <difficult>0</difficult>
        <bndbox>
            <xmin>97</xmin>
            <ymin>0</ymin>
            <xmax>137</xmax>
            <ymax>46</ymax>
        </bndbox>
    </object>    <object>
        <name>helmet</name>
        <pose>Unspecified</pose>
        <truncated>0</truncated>
        <difficult>0</difficult>
        <bndbox>
            <xmin>181</xmin>
            <ymin>99</ymin>
            <xmax>206</xmax>
            <ymax>131</ymax>
        </bndbox>
    </object>    <object>
        <name>helmet</name>
        <pose>Unspecified</pose>
        <truncated>0</truncated>
        <difficult>0</difficult>
        <bndbox>
            <xmin>171</xmin>
            <ymin>133</ymin>
            <xmax>207</xmax>
            <ymax>182</ymax>
        </bndbox>
    </object>    <object>
        <name>helmet</name>
        <pose>Unspecified</pose>
        <truncated>0</truncated>
        <difficult>0</difficult>
        <bndbox>
            <xmin>233</xmin>
            <ymin>95</ymin>
            <xmax>261</xmax>
            <ymax>131</ymax>
        </bndbox>
    </object>    <object>
        <name>helmet</name>
        <pose>Unspecified</pose>
        <truncated>0</truncated>
        <difficult>0</difficult>
        <bndbox>
            <xmin>196</xmin>
            <ymin>0</ymin>
            <xmax>228</xmax>
            <ymax>20</ymax>
        </bndbox>
    </object>    <object>
        <name>helmet</name>
        <pose>Unspecified</pose>
        <truncated>0</truncated>
        <difficult>0</difficult>
        <bndbox>
            <xmin>197</xmin>
            <ymin>119</ymin>
            <xmax>228</xmax>
            <ymax>158</ymax>
        </bndbox>
    </object>    <object>
        <name>helmet</name>
        <pose>Unspecified</pose>
        <truncated>0</truncated>
        <difficult>0</difficult>
        <bndbox>
            <xmin>233</xmin>
            <ymin>4</ymin>
            <xmax>262</xmax>
            <ymax>44</ymax>
        </bndbox>
    </object>    <object>
        <name>helmet</name>
        <pose>Unspecified</pose>
        <truncated>0</truncated>
        <difficult>0</difficult>
        <bndbox>
            <xmin>181</xmin>
            <ymin>6</ymin>
            <xmax>207</xmax>
            <ymax>40</ymax>
        </bndbox>
    </object>    <object>
        <name>helmet</name>
        <pose>Unspecified</pose>
        <truncated>0</truncated>
        <difficult>0</difficult>
        <bndbox>
            <xmin>366</xmin>
            <ymin>0</ymin>
            <xmax>415</xmax>
            <ymax>23</ymax>
        </bndbox>
    </object>
</annotation>
